stimascraper/__about__.py
stimascraper/__init__.py
stimascraper/_logging.py
stimascraper/exceptions.py
stimascraper/scraper.py
stimascraper/utils.py
stima_scraper-1.0.4.dist-info/LICENSE
stima_scraper-1.0.4.dist-info/METADATA
stima_scraper-1.0.4.dist-info/WHEEL
stima_scraper-1.0.4.dist-info/top_level.txt
stima_scraper-1.0.4.dist-info/RECORD
