Metadata-Version: 2.1
Name: stima-scraper
Version: 1.0.4
Summary: A simple kplc pdf scraper
Author-email: Daniel CHege Nduati <dannduati2@gmail.com>
License: MIT License        
Project-URL: Homepage, https://github.com/DanNduati/Stima_scraper
Project-URL: Bug Tracker, https://github.com/DanNduati/Stima_scraper
Keywords: kplc,stima,stimascraper
Classifier: Programming Language :: Python :: 3
Classifier: License :: OSI Approved :: MIT License
Classifier: Operating System :: OS Independent
Requires-Python: >=3.7
License-File: LICENSE
Requires-Dist: requests
Requires-Dist: beautifulsoup4 (>=4.11.1)
Provides-Extra: dev
Requires-Dist: black ; extra == 'dev'
Requires-Dist: bumpver ; extra == 'dev'
Requires-Dist: isort ; extra == 'dev'
Requires-Dist: pip-tools ; extra == 'dev'
Requires-Dist: pytest ; extra == 'dev'
